pypyrus_etl/__init__.py
pypyrus_etl/procs.py
pypyrus_etl/nodes/__init__.py
pypyrus_etl/nodes/database/__init__.py
pypyrus_etl/nodes/database/convs.py
pypyrus_etl/nodes/database/ddl.py
pypyrus_etl/nodes/database/dml.py
pypyrus_etl/nodes/database/func.py
pypyrus_etl/nodes/host/__init__.py
pypyrus_etl/nodes/link/__init__.py
pypyrus_etl/objects/__init__.py
pypyrus_etl/objects/table/__init__.py
pypyrus_etl/pipelines/__init__.py
pypyrus_etl/pipelines/table/__init__.py
pypyrus_etl/pipelines/table/dblink/__init__.py
pypyrus_etl/pipelines/table/dblink/table/__init__.py
pypyrus_etl/pipelines/table/dblink/table/pipeline/__init__.py
pypyrus_etl/pipelines/table/dblink/table/pipeline/objects/__init__.py
pypyrus_etl/pipelines/table/dblink/table/pipeline/objects/eh.py
pypyrus_etl/pipelines/table/dblink/table/pipeline/objects/input.py
pypyrus_etl/pipelines/table/dblink/table/pipeline/objects/medium.py
pypyrus_etl/pipelines/table/dblink/table/pipeline/objects/output.py
pypyrus_etl/pipelines/table/dblink/table/pipeline/procs/__init__.py
pypyrus_etl/pipelines/table/dblink/table/pipeline/procs/extractor.py
pypyrus_etl/pipelines/table/dblink/table/pipeline/procs/loader.py
pypyrus_etl/pipelines/table/dblink/table/pipeline/procs/transformer.py
pypyrus_etl/pipelines/table/dblink/table/pipeline/tools/__init__.py
pypyrus_etl/pipelines/table/dblink/table/pipeline/tools/config.py
pypyrus_etl/pipelines/table/dblink/table/pipeline/tools/log.py
pypyrus_etl/pipelines/table/dblink/table/pipeline/tools/parser.py
pypyrus_etl-0.0.2.dist-info/LICENSE
pypyrus_etl-0.0.2.dist-info/METADATA
pypyrus_etl-0.0.2.dist-info/WHEEL
pypyrus_etl-0.0.2.dist-info/top_level.txt
pypyrus_etl-0.0.2.dist-info/RECORD
